{
    "name": "development",
    "commit": {
        "sha": "d617386a584b7f153faf3ad5824de34a70d12348",
        "node_id": "MDY6Q29tbWl0MTU0NjY1NzYxOmQ2MTczODZhNTg0YjdmMTUzZmFmM2FkNTgyNGRlMzRhNzBkMTIzNDg=",
        "commit": {
            "author": {
                "name": "Deepu K Sasidharan",
                "email": "d4udts@gmail.com",
                "date": "2019-04-17T12:03:56Z"
            },
            "committer": {
                "name": "GitHub",
                "email": "noreply@github.com",
                "date": "2019-04-17T12:03:56Z"
            },
            "message": "Merge pull request #51 from xebialabs/LOVE-821\n\nLOVE-821 Added instructions to blueprints",
            "tree": {
                "sha": "cb85d44bcdf53f1bae080af176baba270e8df970",
                "url": "https://mock.github.com/repos/xebialabs/blueprints/git/trees/cb85d44bcdf53f1bae080af176baba270e8df970"
            },
            "url": "https://mock.github.com/repos/xebialabs/blueprints/git/commits/d617386a584b7f153faf3ad5824de34a70d12348",
            "comment_count": 0,
            "verification": {
                "verified": true,
                "reason": "valid",
                "signature": "-----BEGIN PGP SIGNATURE-----\n\nwsBcBAABCAAQBQJctxYsCRBK7hj4Ov3rIwAAdHIIAHCP3DEo3r5w3BRGj3SOys0W\np7/O/OmiiHBGTYUrskIOORwkkIicwiMpbJZeIRnTpU8R+CDmpTMEh+4k+B2ymw6X\nYEzcD+gi99+6vDKAMzGEG5+H1xg1jpRGho3Z0wsMWkoz6BSUUAW9/EKxFczO/4BO\n8r17TVthycAiMhy1IS0ImTXyIfhga8uvZvuFxZWTDhOiKP7AqadsBPgLcwXslmmq\nHNRDwENYxoaKZiArfcxY4E2B6a0xgD8FTDm2C71jNIFAjLfKC2G4tx5DNZUYs9X+\n/tuOOBOZz6LKkanoPQTD7KjDrpdqoSn1er5SrPjqYB10KttYebxo4Z9L1bhsNmY=\n=ms1/\n-----END PGP SIGNATURE-----\n",
                "payload": "tree cb85d44bcdf53f1bae080af176baba270e8df970\nparent 7c008812cd440e0bf1a16f56ba80ffa7fd5bf2cb\nparent 062e8105f75aef99937d3aa92eb2cffe65aa8b8e\nauthor Deepu K Sasidharan <d4udts@gmail.com> 1555502636 +0200\ncommitter GitHub <noreply@github.com> 1555502636 +0200\n\nMerge pull request #51 from xebialabs/LOVE-821\n\nLOVE-821 Added instructions to blueprints"
            }
        },
        "url": "https://mock.github.com/repos/xebialabs/blueprints/commits/d617386a584b7f153faf3ad5824de34a70d12348",
        "html_url": "https://github.com/xebialabs/blueprints/commit/d617386a584b7f153faf3ad5824de34a70d12348",
        "comments_url": "https://mock.github.com/repos/xebialabs/blueprints/commits/d617386a584b7f153faf3ad5824de34a70d12348/comments",
        "author": {
            "login": "deepu105",
            "id": 1107223,
            "node_id": "MDQ6VXNlcjExMDcyMjM=",
            "avatar_url": "https://avatars2.githubusercontent.com/u/1107223?v=4",
            "gravatar_id": "",
            "url": "https://mock.github.com/users/deepu105",
            "html_url": "https://github.com/deepu105",
            "followers_url": "https://mock.github.com/users/deepu105/followers",
            "following_url": "https://mock.github.com/users/deepu105/following{/other_user}",
            "gists_url": "https://mock.github.com/users/deepu105/gists{/gist_id}",
            "starred_url": "https://mock.github.com/users/deepu105/starred{/owner}{/repo}",
            "subscriptions_url": "https://mock.github.com/users/deepu105/subscriptions",
            "organizations_url": "https://mock.github.com/users/deepu105/orgs",
            "repos_url": "https://mock.github.com/users/deepu105/repos",
            "events_url": "https://mock.github.com/users/deepu105/events{/privacy}",
            "received_events_url": "https://mock.github.com/users/deepu105/received_events",
            "type": "User",
            "site_admin": false
        },
        "committer": {
            "login": "web-flow",
            "id": 19864447,
            "node_id": "MDQ6VXNlcjE5ODY0NDQ3",
            "avatar_url": "https://avatars3.githubusercontent.com/u/19864447?v=4",
            "gravatar_id": "",
            "url": "https://mock.github.com/users/web-flow",
            "html_url": "https://github.com/web-flow",
            "followers_url": "https://mock.github.com/users/web-flow/followers",
            "following_url": "https://mock.github.com/users/web-flow/following{/other_user}",
            "gists_url": "https://mock.github.com/users/web-flow/gists{/gist_id}",
            "starred_url": "https://mock.github.com/users/web-flow/starred{/owner}{/repo}",
            "subscriptions_url": "https://mock.github.com/users/web-flow/subscriptions",
            "organizations_url": "https://mock.github.com/users/web-flow/orgs",
            "repos_url": "https://mock.github.com/users/web-flow/repos",
            "events_url": "https://mock.github.com/users/web-flow/events{/privacy}",
            "received_events_url": "https://mock.github.com/users/web-flow/received_events",
            "type": "User",
            "site_admin": false
        },
        "parents": [
            {
                "sha": "7c008812cd440e0bf1a16f56ba80ffa7fd5bf2cb",
                "url": "https://mock.github.com/repos/xebialabs/blueprints/commits/7c008812cd440e0bf1a16f56ba80ffa7fd5bf2cb",
                "html_url": "https://github.com/xebialabs/blueprints/commit/7c008812cd440e0bf1a16f56ba80ffa7fd5bf2cb"
            },
            {
                "sha": "062e8105f75aef99937d3aa92eb2cffe65aa8b8e",
                "url": "https://mock.github.com/repos/xebialabs/blueprints/commits/062e8105f75aef99937d3aa92eb2cffe65aa8b8e",
                "html_url": "https://github.com/xebialabs/blueprints/commit/062e8105f75aef99937d3aa92eb2cffe65aa8b8e"
            }
        ]
    },
    "_links": {
        "self": "https://mock.github.com/repos/xebialabs/blueprints/branches/development",
        "html": "https://github.com/xebialabs/blueprints/tree/development"
    },
    "protected": false,
    "protection": {
        "enabled": false,
        "required_status_checks": {
            "enforcement_level": "off",
            "contexts": [

            ]
        }
    },
    "protection_url": "https://mock.github.com/repos/xebialabs/blueprints/branches/development/protection"
}
